{
  "BurstVersion": "ca476d69-fe22-4646-a548-58dcbc78df4c",
  "Assemblies": [
    {
      "FullName": "Unity.Burst, Version=0.0.0.0, Culture=neutral, PublicKeyToken=null",
      "LastWriteTime": "2021-11-10T16:39:27.0543397Z"
    },
    {
      "FullName": "mscorlib, Version=4.0.0.0, Culture=neutral, PublicKeyToken=b77a5c561934e089",
      "LastWriteTime": "2021-09-28T06:58:46Z"
    },
    {
      "FullName": "UnityEngine.CoreModule, Version=0.0.0.0, Culture=neutral, PublicKeyToken=null",
      "LastWriteTime": "2021-09-28T07:03:34Z"
    },
    {
      "FullName": "CityGen3D.EditorExtension, Version=1.0.0.0, Culture=neutral, PublicKeyToken=null",
      "LastWriteTime": "2021-11-10T16:19:05.8020986Z"
    },
    {
      "FullName": "mscorlib, Version=2.0.0.0, Culture=neutral, PublicKeyToken=b77a5c561934e089",
      "LastWriteTime": "2021-09-28T06:58:46Z"
    },
    {
      "FullName": "UnityEngine, Version=0.0.0.0, Culture=neutral, PublicKeyToken=null",
      "LastWriteTime": "2021-09-28T07:03:32Z"
    },
    {
      "FullName": "Unity.Mathematics, Version=1.0.0.0, Culture=neutral, PublicKeyToken=null",
      "LastWriteTime": "2021-11-10T16:39:28.3884392Z"
    },
    {
      "FullName": "CityGen3D, Version=1.0.0.0, Culture=neutral, PublicKeyToken=null",
      "LastWriteTime": "2021-11-10T16:19:05.8080975Z"
    },
    {
      "FullName": "Assembly-CSharp, Version=0.0.0.0, Culture=neutral, PublicKeyToken=null",
      "LastWriteTime": "2022-01-13T03:26:13.7864628Z"
    }
  ],
  "Functions": [
    {
      "FullName": "System.Int32 Unity.Burst.Intrinsics.X86::DoGetCSRTrampoline()",
      "ModuleOptionsHash": 11834165633931345063,
      "ModuleHash": "58ca787e0b2e2b98d4a5a39f29176bb0",
      "LinkName": "CDCA4A5193BE5947",
      "AssemblyDependencyIndices": [
        0,
        1
      ]
    },
    {
      "FullName": "System.Void Unity.Burst.Intrinsics.X86::DoSetCSRTrampoline(System.Int32)",
      "ModuleOptionsHash": 11834165633931345063,
      "ModuleHash": "c453d558d531eacbab5b0c3d7aef97f2",
      "LinkName": "801E9A000BB37B05",
      "AssemblyDependencyIndices": [
        0,
        1
      ]
    },
    {
      "FullName": "System.Void Unity.Jobs.IJobParallelForExtensions/ParallelForJobStruct`1<CityGen3D.EditorExtension.Generator/RaycastMapJob>::Execute(T&,System.IntPtr,System.IntPtr,Unity.Jobs.LowLevel.Unsafe.JobRanges&,System.Int32)",
      "ModuleOptionsHash": 11834165633931345063,
      "ModuleHash": "031eb42aa4dafdf5111525a461876c24",
      "LinkName": "A635E3F9A55EF7B8",
      "AssemblyDependencyIndices": [
        2,
        3,
        4,
        1,
        5,
        6
      ]
    },
    {
      "FullName": "System.Void Unity.Jobs.IJobParallelForExtensions/ParallelForJobStruct`1<CityGen3D.EditorExtension.Generator/SpherecastMapJob>::Execute(T&,System.IntPtr,System.IntPtr,Unity.Jobs.LowLevel.Unsafe.JobRanges&,System.Int32)",
      "ModuleOptionsHash": 11834165633931345063,
      "ModuleHash": "ab3242887a4446b17b3c8b961a975259",
      "LinkName": "F31FF4D8DD1DC61B",
      "AssemblyDependencyIndices": [
        2,
        3,
        4,
        1,
        5
      ]
    },
    {
      "FullName": "System.Void Unity.Jobs.IJobParallelForExtensions/ParallelForJobStruct`1<CityGen3D.EditorExtension.Generator/SurfaceResultsJob>::Execute(T&,System.IntPtr,System.IntPtr,Unity.Jobs.LowLevel.Unsafe.JobRanges&,System.Int32)",
      "ModuleOptionsHash": 11834165633931345063,
      "ModuleHash": "bec5eb33a6e16586c6ddc924120e0adc",
      "LinkName": "F3F67E4C9CB15DE8",
      "AssemblyDependencyIndices": [
        2,
        3,
        4,
        5,
        1
      ]
    },
    {
      "FullName": "System.Void Unity.Jobs.IJobParallelForExtensions/ParallelForJobStruct`1<CityGen3D.EditorExtension.Generator/CollisionResultsJob>::Execute(T&,System.IntPtr,System.IntPtr,Unity.Jobs.LowLevel.Unsafe.JobRanges&,System.Int32)",
      "ModuleOptionsHash": 11834165633931345063,
      "ModuleHash": "7ce1f896081be3bc74ecf554cb3fff0c",
      "LinkName": "03D6BE749CDFFFB4",
      "AssemblyDependencyIndices": [
        2,
        3,
        4,
        5,
        1
      ]
    },
    {
      "FullName": "System.Void Unity.Jobs.IJobParallelForExtensions/ParallelForJobStruct`1<CityGen3D.EditorExtension.Generator/TerrainResultsJob>::Execute(T&,System.IntPtr,System.IntPtr,Unity.Jobs.LowLevel.Unsafe.JobRanges&,System.Int32)",
      "ModuleOptionsHash": 11834165633931345063,
      "ModuleHash": "c95b93340698da98284167790b58e7f7",
      "LinkName": "0EB360769685E253",
      "AssemblyDependencyIndices": [
        2,
        3,
        4,
        5,
        1,
        6
      ]
    },
    {
      "FullName": "System.Void Unity.Jobs.IJobParallelForExtensions/ParallelForJobStruct`1<CityGen3D.EditorExtension.Generator/TerrainAltitudeJob>::Execute(T&,System.IntPtr,System.IntPtr,Unity.Jobs.LowLevel.Unsafe.JobRanges&,System.Int32)",
      "ModuleOptionsHash": 11834165633931345063,
      "ModuleHash": "4f85fd0d8669deef0a1b955c2f831b33",
      "LinkName": "DBCEB9ABCA7DDAF5",
      "AssemblyDependencyIndices": [
        2,
        3,
        4,
        5,
        1
      ]
    },
    {
      "FullName": "System.Void Unity.Jobs.IJobParallelForExtensions/ParallelForJobStruct`1<CityGen3D.EditorExtension.Generator/SpherecastColliderJob>::Execute(T&,System.IntPtr,System.IntPtr,Unity.Jobs.LowLevel.Unsafe.JobRanges&,System.Int32)",
      "ModuleOptionsHash": 11834165633931345063,
      "ModuleHash": "a362bca27421a728e66b89b2a6be5af2",
      "LinkName": "E79D7679566BDE5B",
      "AssemblyDependencyIndices": [
        2,
        3,
        4,
        1,
        5
      ]
    },
    {
      "FullName": "System.Void Unity.Jobs.IJobParallelForExtensions/ParallelForJobStruct`1<CityGen3D.EditorExtension.Generator/LevellingJob>::Execute(T&,System.IntPtr,System.IntPtr,Unity.Jobs.LowLevel.Unsafe.JobRanges&,System.Int32)",
      "ModuleOptionsHash": 11834165633931345063,
      "ModuleHash": "3a0ccf3649bfb68d86bda71b491529bc",
      "LinkName": "8912B2CF4DCB4981",
      "AssemblyDependencyIndices": [
        2,
        3,
        4,
        5,
        1
      ]
    },
    {
      "FullName": "System.Void Unity.Jobs.IJobParallelForExtensions/ParallelForJobStruct`1<CityGen3D.EditorExtension.Highways/HighwayResultsJob>::Execute(T&,System.IntPtr,System.IntPtr,Unity.Jobs.LowLevel.Unsafe.JobRanges&,System.Int32)",
      "ModuleOptionsHash": 11834165633931345063,
      "ModuleHash": "b6acc97dce9c0cd7e47f0324bb5b1053",
      "LinkName": "ECCF3F00AAFF1253",
      "AssemblyDependencyIndices": [
        2,
        3,
        4,
        5,
        1
      ]
    },
    {
      "FullName": "System.Void Unity.Jobs.IJobParallelForExtensions/ParallelForJobStruct`1<CityGen3D.EditorExtension.SplatMap/SelectTextureJob>::Execute(T&,System.IntPtr,System.IntPtr,Unity.Jobs.LowLevel.Unsafe.JobRanges&,System.Int32)",
      "ModuleOptionsHash": 11834165633931345063,
      "ModuleHash": "89d2d0caf54a53d1a8ecbc3131e14239",
      "LinkName": "C33ED17DB746D15D",
      "AssemblyDependencyIndices": [
        2,
        3,
        4,
        1,
        5,
        6,
        7
      ]
    },
    {
      "FullName": "System.Void Unity.Jobs.IJobParallelForExtensions/ParallelForJobStruct`1<GleyTrafficSystem.DriveJob>::Execute(T&,System.IntPtr,System.IntPtr,Unity.Jobs.LowLevel.Unsafe.JobRanges&,System.Int32)",
      "ModuleOptionsHash": 11834165633931345063,
      "ModuleHash": "3011390deb2891918ad30704d04b53b5",
      "LinkName": "5786E848FAAEE7A2",
      "AssemblyDependencyIndices": [
        2,
        8,
        4,
        6,
        1
      ]
    },
    {
      "FullName": "System.Void Unity.Jobs.IJobParallelForExtensions/ParallelForJobStruct`1<GleyTrafficSystem.WheelJob>::Execute(T&,System.IntPtr,System.IntPtr,Unity.Jobs.LowLevel.Unsafe.JobRanges&,System.Int32)",
      "ModuleOptionsHash": 11834165633931345063,
      "ModuleHash": "54b3bcf0055860e9471e658effc50e7b",
      "LinkName": "3C122607D82A47C2",
      "AssemblyDependencyIndices": [
        2,
        8,
        4,
        6,
        1
      ]
    },
    {
      "FullName": "System.Void UnityEngine.Jobs.IJobParallelForTransformExtensions/TransformParallelForLoopStruct`1<GleyTrafficSystem.UpdateTriggerJob>::Execute(T&,System.IntPtr,System.IntPtr,Unity.Jobs.LowLevel.Unsafe.JobRanges&,System.Int32)",
      "ModuleOptionsHash": 11834165633931345063,
      "ModuleHash": "7d3e779b4ec55a982983348eb18b0da6",
      "LinkName": "CFEA11BD7AFC4DE6",
      "AssemblyDependencyIndices": [
        2,
        8,
        4,
        1,
        6
      ]
    },
    {
      "FullName": "System.Void UnityEngine.Jobs.IJobParallelForTransformExtensions/TransformParallelForLoopStruct`1<GleyTrafficSystem.UpdateWheelJob>::Execute(T&,System.IntPtr,System.IntPtr,Unity.Jobs.LowLevel.Unsafe.JobRanges&,System.Int32)",
      "ModuleOptionsHash": 11834165633931345063,
      "ModuleHash": "2ed165eb1012557140ee0fb2cd455521",
      "LinkName": "AD3AB413B35559A0",
      "AssemblyDependencyIndices": [
        2,
        8,
        4,
        6,
        1
      ]
    }
  ]
}